boolparser/__init__.py
boolparser/core.py
boolparser-0.3.3.dist-info/LICENSE.md
boolparser-0.3.3.dist-info/METADATA
boolparser-0.3.3.dist-info/WHEEL
boolparser-0.3.3.dist-info/top_level.txt
boolparser-0.3.3.dist-info/RECORD
