Metadata-Version: 2.1
Name: boolparser
Version: 0.3.3
Summary: Boolean Parser
Home-page: http://github.com/eelsirhc/boolparser
Author: Christopher Lee
Author-email: lee@foldmountain.com
License: BSD
Keywords: Boolean,Parsing
Platform: UNKNOWN
Requires-Dist: pyparsing
